charlie/.DS_Store
charlie/__init__.py
charlie/example.py
charlie-0.0.1.dist-info/METADATA
charlie-0.0.1.dist-info/WHEEL
charlie-0.0.1.dist-info/licenses/LICENSE
charlie-0.0.1.dist-info/RECORD
