Metadata-Version: 2.1
Name: charlie
Version: 0.0.1
Summary: Comprehensive High-throughput Analysis of Repeat Length, Interruptions, Etc.
Project-URL: Homepage, https://pypi.org/user/eleanorrobin/
Author-email: Eleanor Robin Heuchan <heuchane@cardiff.ac.uk>
License: Copyright (c) 2018 The Python Packaging Authority
Classifier: License :: OSI Approved :: MIT License
Classifier: Operating System :: OS Independent
Classifier: Programming Language :: Python :: 3
Requires-Python: >=3.7
